pysendyit/__init__.py
pysendyit/api.py
pysendyit/check.py
pysendyit/errors.py
pysendyit/pysendyit.py
pysendyit-0.1.2.dist-info/LICENSE
pysendyit-0.1.2.dist-info/METADATA
pysendyit-0.1.2.dist-info/WHEEL
pysendyit-0.1.2.dist-info/top_level.txt
pysendyit-0.1.2.dist-info/zip-safe
pysendyit-0.1.2.dist-info/RECORD
