Metadata-Version: 2.1
Name: pysendyit
Version: 0.1.2
Summary: Un-Official Sendyit Python wrapper
Home-page: https://github.com/0x6f736f646f/sendit-python
Author: Rodney Osodo
Author-email: blackd0t@protonmail.com
License: MIT
Download-URL: http://pypi.python.org/pypi/pysendy/
Keywords: pysendyit sendy wrapper api
Platform: UNKNOWN
Classifier: Development Status :: 5 - Production/Stable
Classifier: Intended Audience :: Developers
Classifier: License :: OSI Approved :: MIT License
Classifier: Natural Language :: English
Classifier: Operating System :: OS Independent
Classifier: Programming Language :: Python
Classifier: Topic :: Software Development :: Libraries :: Python Modules
Requires-Python: >=3.6
Requires-Dist: requests
